django_snow/__init__.py
django_snow/apps.py
django_snow/models.py
django_snow/helpers/__init__.py
django_snow/helpers/exceptions.py
django_snow/helpers/snow_request_handler.py
django_snow/migrations/0001_initial.py
django_snow/migrations/__init__.py
django_snow-1.0.1.dist-info/DESCRIPTION.rst
django_snow-1.0.1.dist-info/METADATA
django_snow-1.0.1.dist-info/RECORD
django_snow-1.0.1.dist-info/WHEEL
django_snow-1.0.1.dist-info/metadata.json
django_snow-1.0.1.dist-info/top_level.txt
testapp/__init__.py
testapp/settings.py
testapp/tests.py
